slime_nlp/__init__.py
slime_nlp/dataset.py
slime_nlp/model.py
slime_nlp/requirements.txt
slime_nlp/slime.py
slime_nlp-0.1.0.dist-info/LICENSE
slime_nlp-0.1.0.dist-info/WHEEL
slime_nlp-0.1.0.dist-info/METADATA
slime_nlp-0.1.0.dist-info/RECORD
